fastseg/__init__.py
fastseg/image/__init__.py
fastseg/image/colorize.py
fastseg/image/palette.py
fastseg/model/base.py
fastseg/model/efficientnet.py
fastseg/model/lraspp.py
fastseg/model/mobilenetv3.py
fastseg/model/utils.py
fastseg-0.1.2.dist-info/LICENSE.txt
fastseg-0.1.2.dist-info/METADATA
fastseg-0.1.2.dist-info/WHEEL
fastseg-0.1.2.dist-info/top_level.txt
fastseg-0.1.2.dist-info/RECORD
