Metadata-Version: 2.1
Name: fastseg
Version: 0.1.2
Summary: Fast Semantic Segmentation for PyTorch
Home-page: https://github.com/ekzhang/fast-semantic-seg
Author: Eric Zhang
Author-email: ekzhang1@gmail.com
License: MIT
Platform: UNKNOWN
Classifier: Development Status :: 4 - Beta
Classifier: Intended Audience :: Science/Research
Classifier: License :: OSI Approved :: MIT License
Classifier: Programming Language :: Python :: 3
Classifier: Programming Language :: Python :: 3.7
Classifier: Topic :: Scientific/Engineering
Classifier: Topic :: Scientific/Engineering :: Artificial Intelligence
Classifier: Topic :: Scientific/Engineering :: Image Recognition
Classifier: Topic :: Multimedia :: Graphics
Requires-Dist: geffnet (>=0.9.8)
Requires-Dist: Pillow (>=7.0.0)
Requires-Dist: numpy (>=1.18.0)
Requires-Dist: torch (>=1.5.0)
Requires-Dist: torchvision (>=0.6.0)
